opengarage/__init__.py
open_garage-0.2.0.dist-info/LICENSE
open_garage-0.2.0.dist-info/METADATA
open_garage-0.2.0.dist-info/WHEEL
open_garage-0.2.0.dist-info/top_level.txt
open_garage-0.2.0.dist-info/RECORD
